Workbook

Sheet ÍNDICE
B6: NOME DA EMPRESA
B7: ÍNDICE
B11: SHEET
B12: PARÂMETROS
B13: CFOP Considerados
B14: CONFRONTO - ANUAL
B15: CONFRONTO - TRIMESTRAL
B16: CONFRONTO - CONSOLIDAÇÃO
B17: CONFRONTO - ANALITICO

Sheet PARÂMETROS
B6: =ÍNDICE!B6 -> NOME DA EMPRESA
B7: PARÂMETROS
B8: Fonte: https://www.gov.br/receitafederal/pt-br/acesso-a-informacao/acoes-e-programas/facilitacao/2023/ecf
B11: Ref | C11: Arquivo | D11: Descrição
B12: 1. | C12: NF-e | D12: Modelo 55 emitidas pelo contribuinte
B13: 2. | C13: NF-e | D13: CFOPs considerados, conforme link https://www.gov.br/receitafederal/pt-br/acesso-a-informacao/acoes-e-programas/facilitacao/anexo-ecf-cfop
B14: 3. | C14: NF-e | D14: O cálculo do valor das notas fiscais utilizou a seguinte fórmula: (+) Valor dos Produtos e Serviços (–) descontos (+) frete (+) seguros (+) outros (–) ICMS desonerado
B15: 4. | C15: EFD ICMS IPI | D15: Considerados apenas as operações com situação regular - COD_SIT = "00"
B16: 5. | C16: EFD ICMS IPI | D16: Registro C190: “Valor da Operação” subtraído do “Valor ICMS Substituição Tributária” e “Valor IPI”
B17: 6. | C17: EFD ICMS IPI | D17: Registros C320, C390, C490, C590, C690, C790, C850, C890, D190, D410, D590, D690, D696: Apenas o “Valor da Operação”, sem descontos.
B18: 7. | C18: EFD Contribuições | D18: Quando o valor do campo 02 (COD_CONT) for igual a 01, 51, 02, 52, 31 ou 32, o valor do campo será igual à soma dos seguintes campos (quando o CST da operação vinculada for 01, 02, 03, 04, 05 com alíquota diferente de zero)
B19: 8. | C19: EFD Contribuições | D19: VL_ITEM dos registros A170, cujo valor do campo IND_OPER do registro A100 seja igual a “1”,
B20: 9. | C20: EFD Contribuições | D20: VL_ITEM dos registros C170, cujo valor do campo COD_MOD seja diferente de 55 (NFe) ou quando o valor do campo COD_MOD seja igual a 55 e o valor do campo IND_ESCRI do registro C010 seja igual a 2. Em ambos casos o valor do campo IND_OPER do registro C100 deve ser igual a “1”
B21: 10. | C21: EFD Contribuições | D21: VL_ITEM dos registros C181, C185, C491 e C495, quando o valor do campo IND_ESCRI do registro C010 seja igual a 1
B22: 11. | C22: EFD Contribuições | D22: VL_ITEM dos registros C481 e C485 , quando o valor do campo do campo IND_ESCRI do registro C010 seja igual a 2
... B31: 20. | C31: EFD Contribuições | D31: VL_REC do registro I100

Sheet CFOP Considerados
B6: =ÍNDICE!B6 -> NOME DA EMPRESA
B7: CFOPs CONSIDERADOS
B11: Ref | C11: CFOP | D11: Descrição
B12: 1 | C12: 5100 | D12: VENDAS DE PRODUÇÃO PRÓPRIA OU DE TERCEIROS
B13: 2 | C13: 5101 | D13: Venda de produção do estabelecimento
B14: 3 | C14: 5102 | D14: Venda de mercadoria adquirida ou recebida de terceiros
B15: 4 | C15: 5103 | D15: Venda de produção do estabelecimento, efetuada fora do estabelecimento
B16: 5 | C16: 5104 | D16: Venda de mercadoria adquirida ou recebida de terceiros, efetuada fora do estabelecimento
B17: 6 | C17: 5105 | D17: Venda de produção do estabelecimento, que não deva por ele transitar
B18: 7 | C18: 5106 | D18: Venda de mercadoria adquirida ou recebida de terceiros, que não deva por ele transitar
B19: 8 | C19: 5109 | D19: Venda de produção do estabelecimento, destinada à Zona Franca de Manaus ou Áreas de Livre Comércio
B20: 9 | C20: 5110 | D20: Venda de mercadoria adquirida ou recebida de terceiros, destinada à Zona Franca de Manaus ou Áreas de Livre Comércio
B21: 10 | C21: 5111 | D21: Venda de produção do estabelecimento remetida anteriormente em consignação industrial
B22: 11 | C22: 5112 | D22: Venda de mercadoria adquirida ou recebida de terceiros remetida anteriormente em consignação industrial
B23: 12 | C23: 5113 | D23: Venda de produção do estabelecimento remetida anteriormente em consignação mercantil
... B160: 149 | C160: 7667 | D160: Venda de combustível ou lubrificante a consumidor ou usuário final

Sheet CONFRONTO - ANUAL
B6: =ÍNDICE!B6 -> NOME DA EMPRESA
B7: Cruzamento - XML x EFD ICMS IPI x EFD CONTRIBUIÇÕES
C9: =SUBTOTAL(9,C12:C1048576) -> 0 | D9: =SUBTOTAL(9,D12:D1048576) -> 0 | E9: =SUBTOTAL(9,E12:E1048576) -> 0 | F9: =SUBTOTAL(9,F12:F1048576) -> 0 | G9: =SUBTOTAL(9,G12:G1048576) -> 0 | H9: =SUBTOTAL(9,H12:H1048576) -> 0
B10: A | D10: B | E10: C | F10: A - B | G10: A - C | H10: B - C
B11: Ano | C11: XML NFE | D11: EFD ICMS IPI | E11: EFD CONTRIBUIÇÕES | F11: Check - XML x ICMS IPI | G11: Check - XML x CONTRIBUIÇÕES | H11: Check - ICMS IPI x CONTRIBUIÇÕES

Sheet CONFRONTO - TRIMESTRAL
B6: =ÍNDICE!B6 -> NOME DA EMPRESA
B7: Cruzamento - XML x EFD ICMS IPI x EFD CONTRIBUIÇÕES
D9: =SUBTOTAL(9,D12:D1048576) -> 0 | E9: =SUBTOTAL(9,E12:E1048576) -> 0 | F9: =SUBTOTAL(9,F12:F1048576) -> 0 | G9: =SUBTOTAL(9,G12:G1048576) -> 0 | H9: =SUBTOTAL(9,H12:H1048576) -> 0 | I9: =SUBTOTAL(9,I12:I1048576) -> 0
B10: A | E10: B | F10: C | G10: A - B | H10: A - C | I10: B - C
B11: Ano | C11: Trimestre | D11: XML NFE | E11: EFD ICMS IPI | F11: EFD CONTRIBUIÇÕES | G11: Check - XML x ICMS IPI | H11: Check - XML x CONTRIBUIÇÕES | I11: Check - ICMS IPI x CONTRIBUIÇÕES

Sheet CONFRONTO - CONSOLIDAÇÃO
B6: =ÍNDICE!B6 -> NOME DA EMPRESA
B7: Cruzamento - XML x EFD ICMS IPI x EFD CONTRIBUIÇÕES
C9: =SUBTOTAL(9,C12:C1048576) -> 0 | D9: =SUBTOTAL(9,D12:D1048576) -> 0 | E9: =SUBTOTAL(9,E12:E1048576) -> 0 | F9: =SUBTOTAL(9,F12:F1048576) -> 0 | G9: =SUBTOTAL(9,G12:G1048576) -> 0 | H9: =SUBTOTAL(9,H12:H1048576) -> 0
C10: A | D10: B | E10: C | F10: A - B | G10: A - C | H10: B - C
B11: Período | C11: XML NFE | D11: EFD ICMS IPI | E11: EFD CONTRIBUIÇÕES | F11: Check - XML x ICMS IPI | G11: Check - XML x CONTRIBUIÇÕES | H11: Check - ICMS IPI x CONTRIBUIÇÕES
B12: 45444 | C12: ==SOMASE(B12,M12,E12:E1000000)

Sheet CONFRONTO - ANALITICO
B6: =ÍNDICE!B6 -> NOME DA EMPRESA
B7: Cruzamento - XML x EFD ICMS IPI x EFD CONTRIBUIÇÕES
E9: =SUBTOTAL(9,E12:E1048576) -> 0 | G9: =SUBTOTAL(9,G12:G1048576) -> 0 | I9: =SUBTOTAL(9,I12:I1048576) -> 0 | J9: =SUBTOTAL(9,J12:J1048576) -> 0 | K9: =SUBTOTAL(9,K12:K1048576) -> 0 | L9: =SUBTOTAL(9,L12:L1048576) -> 0
C10: A | E10: B | F10: C | G10: D | H10: E | I10: F
B11: Período | C11: CHAVE NFE | D11: Status NF | E11: VL_NFE | F11: EFD ICMS IPI | G11: VL EFD ICMS IPI | H11: EFD CONTRIBUIÇÕES | I11: VL EFD CONTRIBUIÇÕES | J11: Check - XML x ICMS IPI | K11: Check - XML x CONTRIBUIÇÕES | L11: Check - ICMS IPI x CONTRIBUIÇÕES | M11: Trimestre
